<annotation>
	<folder>Camera Roll</folder>
	<filename>b.jpg</filename>
	<path>C:\Users\small.cao\Pictures\Camera Roll\b.jpg</path>
	<source>
		<database>Unknown</database>
	</source>
	<size>
		<width>1080</width>
		<height>1440</height>
		<depth>3</depth>
	</size>
	<segmented>0</segmented>
	<object>
		<name>person</name>
		<pose>Unspecified</pose>
		<truncated>0</truncated>
		<difficult>0</difficult>
		<bndbox>
			<xmin>359</xmin>
			<ymin>605</ymin>
			<xmax>656</xmax>
			<ymax>899</ymax>
		</bndbox>
	</object>
</annotation>
